setup.py
picomongo/__init__.py
picomongo/connection_manager.py
picomongo/document.py
picomongo/exceptions.py
picomongo/utils.py
picomongo.egg-info/PKG-INFO
picomongo.egg-info/SOURCES.txt
picomongo.egg-info/dependency_links.txt
picomongo.egg-info/requires.txt
picomongo.egg-info/top_level.txt