Metadata-Version: 1.1
Name: picomongo
Version: 0.6
Summary: Ultimate MongoDB Object Document Mapper
Home-page: UNKNOWN
Author: Dailymotion IT Team
Author-email: contact@dmcloud.net
License: UNKNOWN
Platform: UNKNOWN
Classifier: Development Status :: 4 - Beta
Classifier: Intended Audience :: Developers
Classifier: License :: OSI Approved :: GNU General Public License v3 (GPLv3)
Classifier: Programming Language :: Python
Classifier: Topic :: Database
